T3ChatApi/__init__.py
T3ChatApi/t3api.py
T3ChatApi-1.4.dist-info/METADATA
T3ChatApi-1.4.dist-info/WHEEL
T3ChatApi-1.4.dist-info/top_level.txt
T3ChatApi-1.4.dist-info/RECORD
