Metadata-Version: 2.1
Name: T3ChatApi
Version: 1.4
Summary: This is an UNOFFICIAL T3 chat API, I built this so you can basically get infinite requests for 8$/Month. Documentation is on Github.
Classifier: Programming Language :: Python :: 3
Classifier: License :: OSI Approved :: MIT License
Classifier: Operating System :: OS Independent
Requires-Python: >=3.6
Requires-Dist: requests
Requires-Dist: typing
Requires-Dist: uuid
